MANIFEST.in
setup.cfg
setup.py
tw/__init__.py
tw.rum.egg-info/PKG-INFO
tw.rum.egg-info/SOURCES.txt
tw.rum.egg-info/dependency_links.txt
tw.rum.egg-info/entry_points.txt
tw.rum.egg-info/namespace_packages.txt
tw.rum.egg-info/not-zip-safe
tw.rum.egg-info/paster_plugins.txt
tw.rum.egg-info/requires.txt
tw.rum.egg-info/rum_i18n.ini
tw.rum.egg-info/top_level.txt
tw.rum.egg-info/i18n/tw.rum.pot
tw.rum.egg-info/i18n/en/LC_MESSAGES/tw.rum.mo
tw.rum.egg-info/i18n/en/LC_MESSAGES/tw.rum.po
tw.rum.egg-info/i18n/es/LC_MESSAGES/tw.rum.mo
tw.rum.egg-info/i18n/es/LC_MESSAGES/tw.rum.po
tw/rum/__init__.py
tw/rum/autocompletion.py
tw/rum/grid.py
tw/rum/paginator.py
tw/rum/querybuilder.py
tw/rum/release.py
tw/rum/repeater.py
tw/rum/samples.py
tw/rum/utc.py
tw/rum/util.py
tw/rum/viewfactory.py
tw/rum/widgets.py
tw/rum/static/.autocompletion.js.swp
tw/rum/static/autocompletion.js
tw/rum/static/cancel.png
tw/rum/static/editpassword.js
tw/rum/static/expandable_span.css
tw/rum/static/expandable_span.js
tw/rum/static/form.css
tw/rum/static/grid.css
tw/rum/static/grid_sort_down.gif
tw/rum/static/grid_sort_up.gif
tw/rum/static/mootools.js
tw/rum/static/pencil.png
tw/rum/static/pencil_add.png
tw/rum/static/pencil_delete.png
tw/rum/static/pencil_go.png
tw/rum/static/repeater.js
tw/rum/static/single_select_preview.js
tw/rum/templates/__init__.py
tw/rum/templates/__init__.pyc
tw/rum/templates/autocompletion.html
tw/rum/templates/binary_link.html
tw/rum/templates/collection_links.html
tw/rum/templates/datagrid.html
tw/rum/templates/default_show.html
tw/rum/templates/expandable_relation_link.html
tw/rum/templates/expandable_span.html
tw/rum/templates/expression.html
tw/rum/templates/image_preview.html
tw/rum/templates/paginator.html
tw/rum/templates/querybuilder.html
tw/rum/templates/relation_link.html
tw/rum/templates/repeater.html
tw/rum/templates/single_select.html
tw/rum/templates/span.html