Metadata-Version: 1.0
Name: tw.rum
Version: 0.2.1
Summary: A ViewFactory for Rum which uses tw.forms
Home-page: http://python-rum.org/
Author: Alberto Valverde Gonzalez, Michael Brickenstein
Author-email: info@python-rum.org
License: UNKNOWN
Keywords: toscawidgets.widgets
Platform: UNKNOWN
Classifier: Development Status :: 3 - Alpha
Classifier: Environment :: Web Environment
Classifier: Environment :: Web Environment :: ToscaWidgets
Classifier: Topic :: Software Development :: Libraries :: Python Modules
Classifier: Topic :: Software Development :: Widget Sets
Classifier: Intended Audience :: Developers
Classifier: Operating System :: OS Independent
Classifier: Programming Language :: Python
